vectorfields/__init__.py
vectorfields/vectorfields.py
vectorfields-0.1.2.dist-info/LICENSE
vectorfields-0.1.2.dist-info/METADATA
vectorfields-0.1.2.dist-info/WHEEL
vectorfields-0.1.2.dist-info/top_level.txt
vectorfields-0.1.2.dist-info/RECORD
