Metadata-Version: 2.1
Name: vectorfields
Version: 0.1.2
Summary: Module for creating vector fields for use in a game engine, e.g. Unreal Engine 4 or Unity 3D.
Home-page: https://github.com/OlafHaag/VectorFields
Author: Olaf Haag
Author-email: haag.olaf@gmail.com
License: UNKNOWN
Project-URL: Bug Reports, https://github.com/OlafHaag/VectorFields/issues
Project-URL: Source, https://github.com/OlafHaag/VectorFields/
Keywords: vector fields FGA vf flowmap unity unreal 3d game engine VFX
Platform: UNKNOWN
Classifier: License :: OSI Approved :: MIT License
Classifier: Programming Language :: Python :: 2.7
Classifier: Programming Language :: Python :: 3
Classifier: Operating System :: OS Independent
Classifier: Environment :: Console
Classifier: Development Status :: 3 - Alpha
Classifier: Intended Audience :: End Users/Desktop
Classifier: Intended Audience :: Science/Research
Classifier: Topic :: Games/Entertainment
Requires-Python: >=2.7
Requires-Dist: numpy
Requires-Dist: matplotlib
